nonebot_weather/__init__.py
nonebot_weather/config.py
nonebot_weather-1.3.dist-info/LICENSE
nonebot_weather-1.3.dist-info/METADATA
nonebot_weather-1.3.dist-info/WHEEL
nonebot_weather-1.3.dist-info/entry_points.txt
nonebot_weather-1.3.dist-info/top_level.txt
nonebot_weather-1.3.dist-info/RECORD
