Metadata-Version: 2.1
Name: nonebot-weather
Version: 1.3
Summary: A small example package
Home-page: https://github.com/hriyel/nonebot-weather.git
Author: hriyel
Author-email: hriyel <1249781871@qq.com>
Project-URL: Homepage, https://github.com/hriyel/nonebot-weather.git
Project-URL: Issues, https://github.com/hriyel/nonebot-weather/issues
Platform: any
Classifier: Programming Language :: Python :: 3
Classifier: License :: OSI Approved :: MIT License
Classifier: Operating System :: OS Independent
Requires-Python: >=3.8
License-File: LICENSE
